hmk1/main.py
hmk1/merkle_proof.py
hmk1/util.py
hmk1-0.1.5.dist-info/LICENSE
hmk1-0.1.5.dist-info/METADATA
hmk1-0.1.5.dist-info/WHEEL
hmk1-0.1.5.dist-info/entry_points.txt
hmk1-0.1.5.dist-info/RECORD
